bffauth/__init__.py
bffauth/handler.py
bffauth/backends/__init__.py
bffauth/backends/authlib.py
bffauth/core/__init__.py
bffauth/core/allowlist.py
bffauth/core/exceptions.py
bffauth/core/models.py
bffauth/core/session.py
bffauth/core/vault.py
bffauth/integrations/__init__.py
bffauth/providers/__init__.py
bffauth/providers/azure.py
bffauth/providers/generic.py
bffauth/providers/github.py
bffauth/providers/google.py
bffauth/storage/__init__.py
bffauth/storage/redis.py
bffauth-0.2.3.dist-info/METADATA
bffauth-0.2.3.dist-info/WHEEL
bffauth-0.2.3.dist-info/licenses/LICENSE
bffauth-0.2.3.dist-info/RECORD
