Metadata-Version: 2.4
Name: bffauth
Version: 0.2.3
Summary: OAuth 2.1 + BFF (Backend-for-Frontend) authentication library for Python
Project-URL: Homepage, https://github.com/ShadNygren/bffauth
Project-URL: Documentation, https://github.com/ShadNygren/bffauth#readme
Project-URL: Repository, https://github.com/ShadNygren/bffauth
Project-URL: Issues, https://github.com/ShadNygren/bffauth/issues
Project-URL: Changelog, https://github.com/ShadNygren/bffauth/blob/main/CHANGELOG.md
Author-email: ShadNygren <shad@hipster.net>
License-Expression: Apache-2.0
License-File: LICENSE
Keywords: authentication,backend-for-frontend,bff,oauth,oauth2,oidc,pkce,security,token-handler
Classifier: Development Status :: 4 - Beta
Classifier: Framework :: FastAPI
Classifier: Framework :: Flask
Classifier: Intended Audience :: Developers
Classifier: License :: OSI Approved :: Apache Software License
Classifier: Operating System :: OS Independent
Classifier: Programming Language :: Python :: 3
Classifier: Programming Language :: Python :: 3.10
Classifier: Programming Language :: Python :: 3.11
Classifier: Programming Language :: Python :: 3.12
Classifier: Topic :: Internet :: WWW/HTTP :: Session
Classifier: Topic :: Security
Classifier: Typing :: Typed
Requires-Python: >=3.10
Requires-Dist: authlib<2.0.0,>=1.3.0
Requires-Dist: cryptography<44.0.0,>=41.0.0
Requires-Dist: httpx<1.0.0,>=0.25.0
Requires-Dist: pydantic-settings<3.0.0,>=2.0.0
Requires-Dist: pydantic<3.0.0,>=2.0.0
Provides-Extra: all
Requires-Dist: fastapi>=0.100.0; extra == 'all'
Requires-Dist: flask>=2.0.0; extra == 'all'
Requires-Dist: redis>=5.0.0; extra == 'all'
Requires-Dist: starlette>=0.27.0; extra == 'all'
Provides-Extra: dev
Requires-Dist: black>=24.0.0; extra == 'dev'
Requires-Dist: mypy>=1.8.0; extra == 'dev'
Requires-Dist: pre-commit>=3.0.0; extra == 'dev'
Requires-Dist: pytest-asyncio>=0.23.0; extra == 'dev'
Requires-Dist: pytest-cov>=4.0.0; extra == 'dev'
Requires-Dist: pytest>=8.0.0; extra == 'dev'
Requires-Dist: ruff>=0.1.0; extra == 'dev'
Provides-Extra: django
Requires-Dist: django>=4.0.0; extra == 'django'
Provides-Extra: docs
Requires-Dist: mkdocs-material>=9.0.0; extra == 'docs'
Requires-Dist: mkdocs>=1.5.0; extra == 'docs'
Requires-Dist: mkdocstrings[python]>=0.24.0; extra == 'docs'
Provides-Extra: fastapi
Requires-Dist: fastapi>=0.100.0; extra == 'fastapi'
Requires-Dist: starlette>=0.27.0; extra == 'fastapi'
Provides-Extra: flask
Requires-Dist: flask>=2.0.0; extra == 'flask'
Provides-Extra: redis
Requires-Dist: redis>=5.0.0; extra == 'redis'
